p2f_HydrateCalcLib/KlaudaSandlerLangParams.csv
p2f_HydrateCalcLib/KlaudaSandlerP_vap.csv
p2f_HydrateCalcLib/Organic Inhibitor Data.csv
p2f_HydrateCalcLib/Salt Data.csv
p2f_HydrateCalcLib/__init__.py
p2f_HydrateCalcLib/componentData.csv
p2f_HydrateCalcLib/core.py
p2f_HydrateCalcLib/hydrateCellProperties.csv
p2f_HydrateCalcLib/interactionParameters.csv
p2f_HydrateCalcLib/model.py
p2f_hydratecalclib-0.1.0.9.dist-info/METADATA
p2f_hydratecalclib-0.1.0.9.dist-info/WHEEL
p2f_hydratecalclib-0.1.0.9.dist-info/RECORD
