Metadata-Version: 2.4
Name: p2f_HydrateCalcLib
Version: 0.1.0.9
Summary: A package providing functionality for the simulation of equilibrium and inhibition of gas hydrates
Project-URL: Homepage, https://github.com/karstenkunneman/p2f_HydrateCalcLib
Project-URL: Issues, https://github.com/karstenkunneman/p2f_HydrateCalcLib/issues
Author-email: Karsten Kunneman <karstenkunneman@protonmail.com>, "Amadeu K. Sum" <asum@mines.edu>
License-Expression: CC-BY-SA-4.0
Classifier: Operating System :: OS Independent
Classifier: Programming Language :: Python :: 3
Requires-Python: <3.13,>=3.9.0
Requires-Dist: matplotlib==3.7.5
Requires-Dist: numpy==1.26.4
Requires-Dist: thermo==0.5.0
